asyncstatsd/__init__.py
asyncstatsd/client/__init__.py
asyncstatsd/client/basic.py
asyncstatsd/client/datadog.py
asyncstatsd/client/udp.py
asyncstatsd/logger.py
asyncstatsd/metrics/__init__.py
asyncstatsd/metrics/basic.py
asyncstatsd/metrics/datadog.py
asyncstatsd/version.py
asyncstatsd-1.0.0a0.dist-info/METADATA
asyncstatsd-1.0.0a0.dist-info/WHEEL
asyncstatsd-1.0.0a0.dist-info/RECORD
