Metadata-Version: 2.1
Name: asyncstatsd
Version: 1.0.0a0
Summary: 
Author: Lukasz Jachym
Author-email: lukasz.jachym@gmail.com
Requires-Python: >=3.11,<4.0
Classifier: Programming Language :: Python :: 3
Classifier: Programming Language :: Python :: 3.11
